resuber/__init__.py
resuber/resuber.py
resuber/calculus/__init__.py
resuber/calculus/ml.py
resuber/calculus/signal.py
resuber/calculus/spatial_transformer_1d.py
resuber/utils/__init__.py
resuber/utils/args.py
resuber/utils/dir.py
resuber-1.1.2.data/scripts/resuber
resuber-1.1.2.data/scripts/resuber-merge
resuber-1.1.2.data/scripts/resuber-move
resuber-1.1.2.data/scripts/resuber-translate
resuber-1.1.2.data/scripts/spleeter2resuber
resuber-1.1.2.dist-info/LICENSE
resuber-1.1.2.dist-info/METADATA
resuber-1.1.2.dist-info/WHEEL
resuber-1.1.2.dist-info/top_level.txt
resuber-1.1.2.dist-info/RECORD
