Metadata-Version: 2.1
Name: resuber
Version: 1.1.2
Summary: Software toolbox to re-synchronize and/or translate SRT subtitles from a movie.
Home-page: https://github.com/polak0v/ReSuber
Author: polak0v
Author-email: the_polakov@protonmail.com
License: MIT
Download-URL: https://github.com/polak0v/ReSuber/archive/v1.1.2.tar.gz
Platform: UNKNOWN
Requires-Dist: matplotlib (==3.1.2)
Requires-Dist: pandas (==1.1.2)
Requires-Dist: plotly (==4.10.0)
Requires-Dist: pysubs2 (==0.2.4)
Requires-Dist: scipy (==1.4.1)
Requires-Dist: tensorflow (==2.3.4)
Requires-Dist: tensorflow-probability (==0.11.0)
